my_christophe_test_package/__init__.py
my_christophe_test_package-0.1.6.dist-info/WHEEL
my_christophe_test_package-0.1.6.dist-info/METADATA
my_christophe_test_package-0.1.6.dist-info/RECORD
