Metadata-Version: 2.1
Name: my-christophe-test-package
Version: 0.1.6
Summary: 
Home-page: https://github.com/christophetd/sample-pypi-project
Author: Your Name
Author-email: you@example.com
Requires-Python: >=3.10,<4.0
Classifier: Programming Language :: Python :: 3
Classifier: Programming Language :: Python :: 3.10
Classifier: Programming Language :: Python :: 3.11
Requires-Dist: requests (>=2.28.1,<3.0.0)
Project-URL: Repository, https://github.com/christophetd/sample-pypi-project
